LICENSE
README.md
setup.py
compress_fasttext/__init__.py
compress_fasttext/compress.py
compress_fasttext/decomposition.py
compress_fasttext/evaluation.py
compress_fasttext/feature_extraction.py
compress_fasttext/models.py
compress_fasttext/navec_like.py
compress_fasttext/pq_encoder_light.py
compress_fasttext/prune.py
compress_fasttext/quantization.py
compress_fasttext/utils.py
compress_fasttext.egg-info/PKG-INFO
compress_fasttext.egg-info/SOURCES.txt
compress_fasttext.egg-info/dependency_links.txt
compress_fasttext.egg-info/requires.txt
compress_fasttext.egg-info/top_level.txt