Metadata-Version: 2.1
Name: compress-fasttext
Version: 0.1.5
Summary: A set of tools to compress gensim fasttext models
Home-page: https://github.com/avidale/compress-fasttext
Author: David Dale
Author-email: dale.david@mail.ru
License: MIT
Platform: UNKNOWN
Classifier: Development Status :: 3 - Alpha
Classifier: Programming Language :: Python :: 3
Classifier: License :: OSI Approved :: MIT License
Classifier: Operating System :: OS Independent
Provides-Extra: full
